BOX_KEEP_UPS/BoxKeepUps.py
BOX_KEEP_UPS-1.dist-info/LICENSE
BOX_KEEP_UPS-1.dist-info/METADATA
BOX_KEEP_UPS-1.dist-info/WHEEL
BOX_KEEP_UPS-1.dist-info/entry_points.txt
BOX_KEEP_UPS-1.dist-info/top_level.txt
BOX_KEEP_UPS-1.dist-info/RECORD
