Metadata-Version: 2.1
Name: BOX-KEEP-UPS
Version: 1
Summary: This package contains implementation of the offline game "BOX_KEEP_UPS" (a simple game created using Kivy).
Home-page: https://github.com/NativeApkDev/BOX_KEEP_UPS
Author: NativeApkDev
Author-email: nativeapkdev2021@gmail.com
License: MIT
Platform: UNKNOWN
Classifier: Programming Language :: Python :: 3
Classifier: Programming Language :: Python :: 3.7
